README.rst
setup.py
istruct/__init__.py
istruct.egg-info/PKG-INFO
istruct.egg-info/SOURCES.txt
istruct.egg-info/dependency_links.txt
istruct.egg-info/top_level.txt
istruct.egg-info/zip-safe